illuminations/__init__.py
illuminations/adapter.py
illuminations/rest.py
illuminations-0.0.4.dist-info/licenses/LICENSE
illuminations-0.0.4.dist-info/METADATA
illuminations-0.0.4.dist-info/WHEEL
illuminations-0.0.4.dist-info/top_level.txt
illuminations-0.0.4.dist-info/RECORD
